cifrepltalk/__init__.py
cifrepltalk-0.0.1.dist-info/LICENSE
cifrepltalk-0.0.1.dist-info/METADATA
cifrepltalk-0.0.1.dist-info/WHEEL
cifrepltalk-0.0.1.dist-info/top_level.txt
cifrepltalk-0.0.1.dist-info/RECORD
