Metadata-Version: 2.1
Name: cifrepltalk
Version: 0.0.1
Summary: A Repl.it Talk Bot Framework for Python
Home-page: https://github.com/CIFProject/cifrepltalk
Author: RaidTheWeb
Author-email: therealraidtheweb@gmail.com
License: UNKNOWN
Platform: UNKNOWN
Classifier: Programming Language :: Python :: 3
Classifier: License :: OSI Approved :: MIT License
Classifier: Operating System :: OS Independent
Requires-Python: >=3.6
